{
    "name": "cfg-tools",
    "outputfilename": "cfg-tools",
    "frontend:install": "npm install",
    "frontend:build": "npm run build",
    "frontend:dev:watcher": "npm run dev",
    "frontend:dev:serverUrl": "http://localhost:3000",
    "author": {
        "name": "User"
    },
    "info": {
        "companyName": "cfg-tools",
        "productName": "cfg-tools",
        "productVersion": "1.0.6",
        "copyright": "Copyright",
        "comments": "DayZ Config Generator"
    },
    "version": "2"
}
